Workbook

Sheet Cover & Assumptions
A1: MERIDIAN TRUST BANK — M&A MERGER MODEL
A2: Project Northfield (Bank B) vs. Project Harborview (Bank C) | Board decision support
A3: Anchor year FY2025 (YE 31 Dec 2025) | CAD $ millions unless noted | Jurisdiction: Canada (fictional)
A5: FICTIONAL / SIMULATED DATA — All entities, financial figures, and events in this document are entirely fictional, created for illustrative/educational simulation purposes. They do not represent any real institution, and nothing here is financial, investment, or M&A advice.
A9: LEGEND & MODEL CONVENTIONS
A10: Blue text = hardcoded input / scenario lever taken from the case source spec
A11: Black text = formula computed on this sheet
A12: Green text = link to another worksheet in this workbook
A13: Yellow fill = headline output the board should read first
A14: All FY2025 anchor figures and all deal terms are taken verbatim from the case spec and are NOT re-derived.
A15: Forward-projection drivers (FY2026E-FY2028E) are model assumptions, disclosed in full below.
A16: Every derived figure in this workbook is a live formula — no hardcoded results.
A18: GLOBAL ASSUMPTIONS
A19: Item | B19: Value | D19: Source / note
A20: Tax rate | B20: 0.26 | D20: Case spec — applies to all synergy / EPS / return math
A21: Meridian internal CET1 target | B21: 0.11 | D21: Case spec s.5 — the trigger for sizing an equity raise
A22: Regulatory CET1 minimum incl. conservation buffer | B22: 0.07 | D22: 4.5% Pillar 1 + 2.5% CCB (fictional OSFI analog)
A23: Meridian share price ($/share) | B23: 44 | D23: 1.6x book on 3,300 equity / 120mm shares (case spec s.2)
A24: Meridian shares outstanding (mm) | B24: 120 | D24: Case spec s.2
A25: Short-term reinvestment / opportunity cost rate | B25: 0.03 | D25: MODEL ASSUMPTION — applied symmetrically to cash deployed and to new-equity proceeds held
A26: Terminal / exit P/E multiple (x) | B26: 12 | D26: MODEL ASSUMPTION — set below Meridian's own 12.8x; used only in the deal IRR
A27: Credit conversion factor on undrawn card lines | B27: 0.1 | D27: Basel III finalisation, unconditionally cancellable lines (spec s.0)
A28: Risk weight — revolver | B28: 0.75 | D28: Case spec s.0
A29: Risk weight — transactor | B29: 0.45 | D29: Case spec s.0
A30: Interchange rate on card purchase volume | B30: 0.015 | D30: Case spec s.0
A32: FORWARD-PROJECTION DRIVERS (FY2026E - FY2028E) — MODEL ASSUMPTIONS
A33: Driver (annual growth) | B33: Bank A | C33: Bank B | D33: Bank C | E33: Basis
A34: Interest income and interest expense | B34: 0.045 | C34: 0.1 | D34: 0.03 | E34: A: 4.5% asset CAGR (spec s.2). B: 24% historical receivable growth deliberately more than halved post-close as Meridian tightens underwriting. C: 2.5-3.0% asset CAGR (spec s.4).
A35: Non-interest income | B35: 0.045 | C35: 0.1 | D35: 0.03 | E35: Tracks the earning book
A36: Provision for credit losses | B36: 0.05 | C36: 0.15 | D36: 0.04 | E36: B is set deliberately ABOVE its receivable growth, per spec s.3: 'provision expense growing faster than receivables'
A37: Non-interest expense | B37: 0.035 | C37: 0.06 | D37: 0.03 | E37: A: positive operating leverage delivers the 5-6% net income growth in spec s.2
A38: Gross card receivables and undrawn lines | B38: 0.06 | C38: 0.1 | D38: 0.04 | E38: A and C per spec s.2 / s.4; B moderated post-close
A40: DEAL B — MERIDIAN ACQUIRES NORTHFIELD CARD BANK (all cash)
A41: Term | B41: Value | D41: Source / note
A42: Purchase price ($mm, all cash) | B42: 1650 | D42: Case spec s.5
A43: Northfield standalone implied value ($mm) | B43: 1320 | D43: 1.47x FY2025 book (spec s.3)
A44: Share funded with new senior debt | B44: 0.7 | D44: Case spec s.5
A45: New senior debt ($mm) | B45: ='Cover & Assumptions'!$B$42*'Cover & Assumptions'!$B$44 -> 1155
A46: Meridian cash / excess capital deployed ($mm) | B46: ='Cover & Assumptions'!$B$42-'Cover & Assumptions'!$B$45 -> 495
A47: Senior debt coupon | B47: 0.0525 | D47: Case spec s.5
A48: Cost synergies as % of target FY2025 opex | B48: 0.3 | D48: Case spec s.5
A49: Cost synergies run-rate ($mm) | B49: ='Cover & Assumptions'!$B$48*'Standalone Summary'!$C$39 -> 192
A50: Cost synergy phase-in — Year 1 | B50: 0.4 | D50: Case spec s.5
A51: Cost synergy phase-in — Year 2 | B51: 0.8 | D51: Case spec s.5
A52: Cost synergy phase-in — Year 3 | B52: 1 | D52: Case spec s.5
A53: Revenue synergy — broker funding replaced ($mm) | B53: 2000 | D53: Case spec s.5: cheaper Meridian deposits substitute for Northfield broker funding
A54: Revenue synergy — funding spread saved | B54: 0.015 | D54: Case spec s.5 (~150bps)
A55: Funding substitution benefit ($mm) | B55: ='Cover & Assumptions'!$B$53*'Cover & Assumptions'!$B$54 -> 30
A56: Revenue synergy — cross-sell uplift on combined card fee income | B56: 0.05 | D56: Case spec s.5
A57: Combined FY2025 interchange & card fee income ($mm) | B57: ='Standalone Summary'!$B$34+'Standalone Summary'!$C$34 -> 310
A58: Cross-sell interchange benefit ($mm) | B58: ='Cover & Assumptions'!$B$56*'Cover & Assumptions'!$B$57 -> 15.5
A59: TOTAL revenue synergies run-rate ($mm) | B59: ='Cover & Assumptions'!$B$55+'Cover & Assumptions'!$B$58 -> 45.5
A60: Revenue synergy phase-in — Year 1 | B60: 0.5 | D60: Spec s.5 says 'phased in by Year 2' — modelled as half in Year 1, full from Year 2
A61: Revenue synergy phase-in — Year 2 | B61: 1
A62: Revenue synergy phase-in — Year 3 | B62: 1
A63: One-time integration / restructuring cost ($mm pretax, Year 1) | B63: 180 | D63: Case spec s.5 — tech integration plus compliance remediation given the regulatory history
A64: Day-1 IFRS 9 provisioning gross-up ($mm) | B64: 115 | D64: Case spec s.5 — allowance build beyond the allowance Northfield already carries
A66: DEAL C — MERIDIAN ACQUIRES HARBORVIEW COMMUNITY BANK (all cash)
A67: Term | B67: Value | D67: Source / note
A68: Purchase price ($mm, all cash) | B68: 1050 | D68: Case spec s.5
A69: Harborview standalone implied value ($mm) | B69: 880 | D69: 1.10x FY2025 book (spec s.4)
A70: Share funded with new senior debt | B70: 0.5 | D70: Case spec s.5
A71: New senior debt ($mm) | B71: ='Cover & Assumptions'!$B$68*'Cover & Assumptions'!$B$70 -> 525
A72: Meridian cash / excess capital deployed ($mm) | B72: ='Cover & Assumptions'!$B$68-'Cover & Assumptions'!$B$71 -> 525
A73: Senior debt coupon | B73: 0.0485 | D73: Case spec s.5 — lower rate reflecting the lower-risk deal
A74: Cost synergies as % of target FY2025 opex | B74: 0.45 | D74: Case spec s.5
A75: Cost synergies run-rate ($mm) | B75: ='Cover & Assumptions'!$B$74*'Standalone Summary'!$D$39 -> 87.75
A76: Cost synergy phase-in — Year 1 | B76: 0.5 | D76: Branch and back-office overlap consolidates faster than tech/risk integration (spec s.5)
A77: Cost synergy phase-in — Year 2 | B77: 0.85 | D77: Case spec s.5
A78: Cost synergy phase-in — Year 3 | B78: 1 | D78: Case spec s.5
A79: Revenue synergy — uplift to combined card purchase volume | B79: 0.15 | D79: Case spec s.5: Harborview's underwriting model cross-sold across a slice of Meridian's prime deposit base, within two years
A80: Combined FY2025 card purchase volume ($mm) | B80: ='Standalone Summary'!$B$65+'Standalone Summary'!$D$65 -> 5450
A81: Incremental interchange from cross-sell ($mm) | B81: ='Cover & Assumptions'!$B$80*'Cover & Assumptions'!$B$79*'Cover & Assumptions'!$B$30 -> 12.2625
A82: Revenue synergy — blended funding-cost improvement | B82: 0.001 | D82: Case spec s.5 (~10bps), sourced from Harborview's 6,300 chequing/savings base
A83: Combined interest-bearing liabilities ($mm) | B83: ='Standalone Summary'!$B$27+'Standalone Summary'!$D$27 -> 45550
A84: Funding-cost benefit ($mm) | B84: ='Cover & Assumptions'!$B$82*'Cover & Assumptions'!$B$83 -> 45.55
A85: TOTAL revenue synergies run-rate ($mm) | B85: ='Cover & Assumptions'!$B$81+'Cover & Assumptions'!$B$84 -> 57.8125
A86: Revenue synergy phase-in — Year 1 | B86: 0.5 | D86: Spec s.5 says 'within 2 years' — modelled as half in Year 1, full from Year 2
A87: Revenue synergy phase-in — Year 2 | B87: 1
A88: Revenue synergy phase-in — Year 3 | B88: 1
A89: One-time integration / restructuring cost ($mm pretax, Year 1) | B89: 95 | D89: Case spec s.5
A90: Day-1 IFRS 9 provisioning gross-up ($mm) | B90: 12 | D90: Case spec s.5
A92: STRESS SCENARIO ASSUMPTIONS (case spec s.7)
A93: Parameter | B93: Value | D93: Source / note
A94: Net charge-off uplift — ACQUIRED card portfolios (B and C) | B94: 0.02 | D94: Case spec s.7: +200bps
A95: 90+ DPD uplift — ACQUIRED card portfolios | B95: 0.015 | D95: Case spec s.7: +150bps
A96: Net charge-off uplift — Meridian's existing card book | B96: 0.005 | D96: Case spec s.7: +50bps; prime and transactor-heavy, so it flexes less
A97: EAD migration — share of undrawn lines drawn under stress | B97: 0.05 | D97: MODEL OVERLAY: distressed borrowers draw down before they default, converting exposure from a 10% CCF to on-balance-sheet at 75% RW
A98: Stress year modelled: FY2026E (Year 1 post-close), the most binding point for pro forma capital. The stress is applied to the card portfolios only; every other line is held at base case.

Sheet Standalone Summary
A1: STANDALONE SUMMARY — FY2025 ANCHOR FINANCIALS AND FORWARD PROJECTIONS
A2: Bank A Meridian Trust | Bank B Northfield Card | Bank C Harborview Community
A3: Every FY2025 figure is a case-spec anchor entered verbatim (blue). Everything else is computed.
A5: FICTIONAL / SIMULATED DATA — All entities, financial figures, and events in this document are entirely fictional, created for illustrative/educational simulation purposes. They do not represent any real institution, and nothing here is financial, investment, or M&A advice.
A9: FY2025 BALANCE SHEET ($mm)
A10: Line item | B10: Bank A Meridian Trust | C10: Bank B Northfield Card | D10: Bank C Harborview Comm. | F10: Note
A11: Cash & equivalents | B11: 1800 | C11: 650 | D11: 520
A12: Investment securities | B12: 6200 | C12: 900 | D12: 1650
A13: Residential mortgages | B13: 19500 | C13: 0 | D13: 4900
A14: Commercial & business loans | B14: 8400 | C14: 0 | D14: 1450
A15: Credit card receivables (net) | B15: 1150 | C15: 7200 | D15: 340
A16: Other consumer loans | B16: 2950 | C16: 1150 | D16: 640
A17: Other assets | B17: 1000 | C17: 500 | D17: 300
A18: Total assets | B18: =SUM(B11:B17) -> 41000 | C18: =SUM(C11:C17) -> 10400 | D18: =SUM(D11:D17) -> 9800
A20: Total deposits | B20: 32500 | C20: 6100 | D20: 8200 | F20: A: 21,000 chequing/savings + 11,500 term/GIC. B: broker / direct-to-consumer. C: 6,300 chequing/savings + 1,900 term.
A21: Wholesale borrowings / securitization debt | B21: 4300 | C21: 2900 | D21: 550
A22: Other liabilities | B22: 900 | C22: 500 | D22: 250
A23: Total liabilities | B23: =SUM(B20:B22) -> 37700 | C23: =SUM(C20:C22) -> 9500 | D23: =SUM(D20:D22) -> 9000
A24: Common equity | B24: 3300 | C24: 900 | D24: 800
A25: Total liabilities & equity | B25: =B23+B24 -> 41000 | C25: =C23+C24 -> 10400 | D25: =D23+D24 -> 9800
A26: Check: total assets less total liabilities & equity | B26: =B18-B25 -> 0 | C26: =C18-C25 -> 0 | D26: =D18-D25 -> 0 | F26: Must be nil — confirms the spec's balance sheets tie out
A27: Memo: interest-bearing liabilities (deposits + wholesale) | B27: =B20+B21 -> 36800 | C27: =C20+C21 -> 9000 | D27: =D20+D21 -> 8750
A29: FY2025 INCOME STATEMENT ($mm)
A30: Line item | B30: Bank A | C30: Bank B | D30: Bank C | F30: Note
A31: Interest income | B31: 1780 | C31: 1540 | D31: 415
A32: Interest expense | B32: 820 | C32: 290 | D32: 165
A33: Net interest income | B33: =B31-B32 -> 960 | C33: =C31-C32 -> 1250 | D33: =D31-D32 -> 250
A34: Interchange & card fee income | B34: 64 | C34: 246 | D34: 21 | F34: B: 15,300 purchase volume x 1.5% interchange, plus fees
A35: Other fee income | B35: 410 | C35: 0 | D35: 38
A36: Non-interest income | B36: =B34+B35 -> 474 | C36: =C34+C35 -> 246 | D36: =D34+D35 -> 59
A37: Total revenue | B37: =B33+B36 -> 1434 | C37: =C33+C36 -> 1496 | D37: =D33+D36 -> 309
A38: Provision for credit losses | B38: 96 | C38: 385 | D38: 14
A39: Non-interest expense (opex) | B39: 780 | C39: 640 | D39: 195
A40: Pre-tax income | B40: =B37-B38-B39 -> 558 | C40: =C37-C38-C39 -> 471 | D40: =D37-D38-D39 -> 100
A41: Income tax | B41: =B40*'Cover & Assumptions'!$B$20 -> 145.08 | C41: =C40*'Cover & Assumptions'!$B$20 -> 122.46 | D41: =D40*'Cover & Assumptions'!$B$20 -> 26
A42: Net income | B42: =B40-B41 -> 412.92 | C42: =C40-C41 -> 348.54 | D42: =D40-D41 -> 74
A44: FY2025 CAPITAL & REGULATORY RATIOS
A45: Line item | B45: Bank A | C45: Bank B | D45: Bank C | F45: Note
A46: CET1 capital ($mm) | B46: 3050 | C46: 790 | D46: 760
A47: Risk-weighted assets ($mm) | B47: 22600 | C47: 6850 | D47: 4450
A48: CET1 ratio | B48: =B46/B47 -> 0.13495575 | C48: =C46/C47 -> 0.11532847 | D48: =D46/D47 -> 0.17078652
A49: Leverage ratio (as reported) | B49: 0.076 | C49: 0.087 | D49: 0.082 | F49: Spec-given; the leverage exposure measure differs from balance-sheet assets
A50: Implied regulatory deductions (equity less CET1) | B50: =B24-B46 -> 250 | C50: =C24-C46 -> 110 | D50: =D24-D46 -> 40 | F50: Existing goodwill, intangibles and other CET1 deductions
A51: RWA density (RWA / total assets) | B51: =B47/B18 -> 0.55121951 | C51: =C47/C18 -> 0.65865385 | D51: =D47/D18 -> 0.45408163 | F51: Bank B's density reflects a revolver-heavy book sitting in the 75% RW bucket
A53: FY2025 CREDIT CARD PORTFOLIO DETAIL
A54: Line item | B54: Bank A | C54: Bank B | D54: Bank C | F54: Note
A55: Active accounts (000s) | B55: 480 | C55: 2850 | D55: 145
A56: Gross receivables ($mm) | B56: 1190 | C56: 7550 | D56: 355
A57: Allowance for credit losses ($mm) | B57: 40 | C57: 350 | D57: 15
A58: Net receivables ($mm) | B58: =B56-B57 -> 1150 | C58: =C56-C57 -> 7200 | D58: =D56-D57 -> 340
A59: Allowance coverage (% of gross) | B59: =B57/B56 -> 0.033613445 | C59: =C57/C56 -> 0.046357616 | D59: =D57/D56 -> 0.042253521 | F59: B carries 4.6% — already elevated, and still short of the Day-1 gross-up an acquirer must book
A60: Average balance per account ($) | B60: =B56*1000/B55 -> 2479.1667 | C60: =C56*1000/C55 -> 2649.1228 | D60: =D56*1000/D55 -> 2448.2759
A61: Revolve rate | B61: 0.4 | C61: 0.71 | D61: 0.35
A62: Average utilization | B62: 0.21 | C62: 0.38 | D62: 0.19
A63: Total committed line exposure ($mm) | B63: 5600 | C63: 19900 | D63: 1780
A64: Undrawn lines ($mm) | B64: =B63-B56 -> 4410 | C64: =C63-C56 -> 12350 | D64: =D63-D56 -> 1425 | F64: The customer's drawdown option — contingent exposure the acquirer also buys
A65: Annual purchase volume ($mm) | B65: 4100 | C65: 15300 | D65: 1350
A66: Posted APR | B66: 0.2099 | C66: 0.2299 | D66: 0.1999
A67: 30+ DPD | B67: 0.016 | C67: 0.038 | D67: 0.011
A68: 90+ DPD | B68: 0.008 | C68: 0.024 | D68: 0.005
A69: Net charge-off rate | B69: 0.019 | C69: 0.046 | D69: 0.012
A70: IFRS 9 Stage 1 (% of gross) | B70: 0.92 | C70: 0.81 | D70: 0.95
A71: IFRS 9 Stage 2 (% of gross) | B71: 0.063 | C71: 0.125 | D71: 0.04
A72: IFRS 9 Stage 3 (% of gross) | B72: 0.017 | C72: 0.065 | D72: 0.01
A73: Blended 12-month PD | B73: 0.021 | C73: 0.054 | D73: 0.014
A74: Loss given default (LGD) | B74: 0.82 | C74: 0.86 | D74: 0.78
A75: Implied 12-month expected loss (PD x LGD x gross, $mm) | B75: =B73*B74*B56 -> 20.4918 | C75: =C73*C74*C56 -> 350.622 | D75: =D73*D74*D56 -> 3.8766
A76: RWA carried on undrawn lines (undrawn x 10% CCF x 75% RW, $mm) | B76: =B64*'Cover & Assumptions'!$B$27*'Cover & Assumptions'!$B$28 -> 330.75 | C76: =C64*'Cover & Assumptions'!$B$27*'Cover & Assumptions'!$B$28 -> 926.25 | D76: =D64*'Cover & Assumptions'!$B$27*'Cover & Assumptions'!$B$28 -> 106.875 | F76: Only a tenth of the committed exposure is capitalised until it converts — see the Stress Test tab
A78: FY2025 KEY RATIOS
A79: Ratio | B79: Bank A | C79: Bank B | D79: Bank C | F79: Note
A80: Return on equity | B80: =B42/B24 -> 0.12512727 | C80: =C42/C24 -> 0.38726667 | D80: =D42/D24 -> 0.0925 | F80: B's 38.8% is a function of a very thin equity base, not of superior underwriting
A81: Return on assets | B81: =B42/B18 -> 0.01007122 | C81: =C42/C18 -> 0.033513462 | D81: =D42/D18 -> 0.0075510204
A82: Efficiency ratio (opex / revenue) | B82: =B39/B37 -> 0.54393305 | C82: =C39/C37 -> 0.42780749 | D82: =D39/D37 -> 0.63106796
A83: Net interest margin (as reported) | B83: 0.0249 | C83: 0.15 | D83: 0.0273 | F83: Spec-given; B is measured on receivables, A and C on earning assets
A84: Earnings per share ($) — Bank A | B84: =B42/'Cover & Assumptions'!$B$24 -> 3.441
A85: Book value per share ($) — Bank A | B85: =B24/'Cover & Assumptions'!$B$24 -> 27.5
A86: Market capitalisation ($mm) — Bank A | B86: ='Cover & Assumptions'!$B$24*'Cover & Assumptions'!$B$23 -> 5280
A87: Price / book (x) — Bank A | B87: ='Cover & Assumptions'!$B$23/B85 -> 1.6
A88: Price / earnings (x) — Bank A | B88: ='Cover & Assumptions'!$B$23/B84 -> 12.786981
A90: THREE-YEAR TREND — THE DILIGENCE SIGNAL (FY2023A - FY2025A)
A91: Metric | B91: FY2023A | C91: FY2024A | D91: FY2025A | F91: Direction
A92: Bank A — Meridian Trust
A93: Gross card receivables ($mm) | B93: =D93/(1+'Cover & Assumptions'!$B$38)^2 -> 1059.0958 | C93: =D93/(1+'Cover & Assumptions'!$B$38) -> 1122.6415 | D93: 1190
A94: 90+ DPD | B94: 0.009 | C94: 0.0085 | D94: 0.008 | F94: Improving
A95: Net charge-off rate | B95: 0.02 | C95: 0.0195 | D95: 0.019 | F95: Improving
A96: CET1 ratio | B96: 0.132 | C96: 0.134 | D96: 0.135 | F96: Stable and strong
A97: Bank B — Northfield Card
A98: Gross card receivables ($mm) | B98: 4910 | C98: 6090 | D98: 7550 | F98: Spec s.3: ~24% CAGR
A99: Annual purchase volume ($mm) | B99: 10113 | C99: 12439 | D99: 15300 | F99: ~23% per year
A100: Provision for credit losses ($mm) | B100: 214 | C100: 287 | D100: 385 | F100: ~+34% per year — outrunning the book
A101: PCL as % of gross receivables | B101: =B100/B98 -> 0.043584521 | C101: =C100/C98 -> 0.047126437 | D101: =D100/D98 -> 0.050993377 | F101: RISING — credit cost is growing faster than the asset generating it
A102: 90+ DPD | B102: 0.015 | C102: 0.019 | D102: 0.024 | F102: WORSENING (spec s.3)
A103: Net charge-off rate | B103: 0.03 | C103: 0.037 | D103: 0.046 | F103: WORSENING (spec s.3)
A104: CET1 ratio | B104: 0.135 | C104: 0.124 | D104: 0.115 | F104: DECLINING — RWA growth outpacing internal capital generation (spec s.3)
A105: Bank C — Harborview Community
A106: Gross card receivables ($mm) | B106: =D106/(1+'Cover & Assumptions'!$D$38)^2 -> 328.21746 | C106: =D106/(1+'Cover & Assumptions'!$D$38) -> 341.34615 | D106: 355
A107: 90+ DPD | B107: 0.005 | C107: 0.005 | D107: 0.005 | F107: Stable and excellent
A108: Net charge-off rate | B108: 0.012 | C108: 0.012 | D108: 0.012 | F108: Stable and excellent
A109: CET1 ratio | B109: 0.165 | C109: 0.168 | D109: 0.171 | F109: Stable and high
A110: Bank B is the only one of the three whose credit quality AND capital ratio both deteriorated over the trend window, while its book grew fastest. That combination — growth outrunning risk systems — is the strongest diligence argument in this case, and it is invisible in the FY2025 snapshot alone.
...

Sheet Deal B Pro Forma
A1: DEAL B PRO FORMA — PROJECT NORTHFIELD
A2: Meridian Trust Bank acquires Northfield Card Bank — all-cash acquisition
A3: Purchase accounting, pro forma balance sheet, capital walk and three-year accretion / dilution ($mm unless noted)
A5: FICTIONAL / SIMULATED DATA — All entities, financial figures, and events in this document are entirely fictional, created for illustrative/educational simulation purposes. They do not represent any real institution, and nothing here is financial, investment, or M&A advice.
A9: A. PURCHASE PRICE, VALUATION AND GOODWILL
A10: Item | B10: Amount | F10: Derivation / note
A11: Purchase price (all cash) | B11: ='Cover & Assumptions'!$B$42 -> 1650 | F11: Case spec s.5
A12: Target common equity at close (book) | B12: ='Standalone Summary'!$C$24 -> 900 | F12: Northfield Card Bank FY2025 book equity
A13: Less: Day-1 IFRS 9 provisioning gross-up | B13: =-'Cover & Assumptions'!$B$64 -> -115 | F13: Acquisition-accounting allowance build beyond the allowance already carried
A14: Net identifiable assets acquired | B14: =B12+B13 -> 785
A15: GOODWILL CREATED | B15: =B11-B14 -> 865 | F15: Purchase price less (target book equity less the Day-1 provision build)
A17: Implied price / book (x) | B17: =B11/B12 -> 1.8333333
A18: Implied price / FY2025 earnings (x) | B18: =B11/'Standalone Summary'!$C$42 -> 4.7340334
A19: Premium to standalone implied value | B19: =B11/'Cover & Assumptions'!$B$43-1 -> 0.25 | F19: Standalone value per case spec
A20: FY2025 earnings yield on purchase price | B20: ='Standalone Summary'!$C$42/B11 -> 0.21123636 | F20: Compare against the after-tax cost of the acquisition debt below — the gap is what drives accretion
A21: After-tax cost of acquisition debt | B21: ='Cover & Assumptions'!$B$47*(1-'Cover & Assumptions'!$B$20) -> 0.03885
A22: Spread of earnings yield over after-tax debt cost | B22: =B20-B21 -> 0.17238636
A24: B. SOURCES AND USES OF FUNDS
A25: Item | B25: Amount | C25: % of total | F25: Note
A26: Source: new senior debt | B26: ='Cover & Assumptions'!$B$45 -> 1155 | C26: =B26/B28 -> 0.7
A27: Source: Meridian cash / excess capital | B27: ='Cover & Assumptions'!$B$46 -> 495 | C27: =B27/B28 -> 0.3
A28: Total sources | B28: =B26+B27 -> 1650
A29: Use: cash consideration to target shareholders | B29: =B11 -> 1650
A30: Total uses | B30: =B29 -> 1650
A31: Memo: one-time integration cost, expensed in Year 1 (pretax) | B31: ='Cover & Assumptions'!$B$63 -> 180
A33: C. PRO FORMA COMBINED BALANCE SHEET AT CLOSE ($mm)
A34: Line item | B34: Bank A FY2025A | C34: Northfield Card Bank FY2025A | D34: Deal adjustments | E34: Pro forma combined | F34: Adjustment note
A35: Cash & equivalents | B35: ='Standalone Summary'!$B$11 -> 1800 | C35: ='Standalone Summary'!$C$11 -> 650 | D35: =-'Cover & Assumptions'!$B$46+B68 -> 559.5 | E35: =B35+C35+D35 -> 3009.5 | F35: Less the cash consideration funded from Meridian's own funds; plus any new equity proceeds
A36: Investment securities | B36: ='Standalone Summary'!$B$12 -> 6200 | C36: ='Standalone Summary'!$C$12 -> 900 | D36: 0 | E36: =B36+C36+D36 -> 7100
A37: Residential mortgages | B37: ='Standalone Summary'!$B$13 -> 19500 | C37: ='Standalone Summary'!$C$13 -> 0 | D37: 0 | E37: =B37+C37+D37 -> 19500
A38: Commercial & business loans | B38: ='Standalone Summary'!$B$14 -> 8400 | C38: ='Standalone Summary'!$C$14 -> 0 | D38: 0 | E38: =B38+C38+D38 -> 8400
A39: Credit card receivables (net) | B39: ='Standalone Summary'!$B$15 -> 1150 | C39: ='Standalone Summary'!$C$15 -> 7200 | D39: =-'Cover & Assumptions'!$B$64 -> -115 | E39: =B39+C39+D39 -> 8235 | F39: Day-1 IFRS 9 provisioning gross-up
A40: Other consumer loans | B40: ='Standalone Summary'!$B$16 -> 2950 | C40: ='Standalone Summary'!$C$16 -> 1150 | D40: 0 | E40: =B40+C40+D40 -> 4100
A41: Goodwill created on acquisition | B41: 0 | C41: 0 | D41: =B15 -> 865 | E41: =B41+C41+D41 -> 865 | F41: A straight CET1 deduction — see the capital walk below
A42: Other assets | B42: ='Standalone Summary'!$B$17 -> 1000 | C42: ='Standalone Summary'!$C$17 -> 500 | D42: 0 | E42: =B42+C42+D42 -> 1500
A43: Total assets | B43: =SUM(B35:B42) -> 41000 | C43: =SUM(C35:C42) -> 10400 | D43: =SUM(D35:D42) -> 1309.5 | E43: =SUM(E35:E42) -> 52709.5
A45: Total deposits | B45: ='Standalone Summary'!$B$20 -> 32500 | C45: ='Standalone Summary'!$C$20 -> 6100 | D45: 0 | E45: =B45+C45+D45 -> 38600
A46: Wholesale borrowings / securitization debt | B46: ='Standalone Summary'!$B$21 -> 4300 | C46: ='Standalone Summary'!$C$21 -> 2900 | D46: ='Cover & Assumptions'!$B$45 -> 1155 | E46: =B46+C46+D46 -> 8355 | F46: New senior acquisition debt raised
A47: Other liabilities | B47: ='Standalone Summary'!$B$22 -> 900 | C47: ='Standalone Summary'!$C$22 -> 500 | D47: 0 | E47: =B47+C47+D47 -> 1400
A48: Total liabilities | B48: =SUM(B45:B47) -> 37700 | C48: =SUM(C45:C47) -> 9500 | D48: =SUM(D45:D47) -> 1155 | E48: =SUM(E45:E47) -> 48355
A49: Common equity | B49: ='Standalone Summary'!$B$24 -> 3300 | C49: ='Standalone Summary'!$C$24 -> 900 | D49: =-'Standalone Summary'!$C$24+B68 -> 154.5 | E49: =B49+C49+D49 -> 4354.5 | F49: Target equity is eliminated in purchase accounting; acquirer equity is unchanged apart from any new issuance
A50: Total liabilities & equity | E50: =E48+E49 -> 52709.5
A51: Check: pro forma assets less liabilities & equity | E51: =E43-E50 -> 0 | F51: Must be nil
A53: D. PRO FORMA CAPITAL WALK AND EQUITY RAISE SIZING
A54: Item | B54: Amount | F54: Note
A55: Bank A standalone CET1 capital | B55: ='Standalone Summary'!$B$46 -> 3050
A56: Less: goodwill created on acquisition (full CET1 deduction) | B56: =-B15 -> -865 | F56: All-cash structure — no shares are issued, so nothing offsets the deduction
A57: Pro forma CET1 capital — BEFORE any equity raise | B57: =B55+B56 -> 2185
A58: Bank A standalone RWA | B58: ='Standalone Summary'!$B$47 -> 22600
A59: Plus: Northfield Card Bank RWA acquired | B59: ='Standalone Summary'!$C$47 -> 6850
A60: Pro forma combined RWA | B60: =B58+B59 -> 29450
A61: PRO FORMA CET1 RATIO — before equity raise | B61: =B57/B60 -> 0.074193548
A62: Memo: Bank A standalone CET1 ratio, pre-deal | B62: ='Standalone Summary'!$B$48 -> 0.13495575
A63: Change in CET1 ratio versus standalone (bps) | B63: =(B61-B62)*10000 -> -607.62204
A65: Meridian internal CET1 target | B65: ='Cover & Assumptions'!$B$21 -> 0.11
A66: CET1 capital required to hold the target | B66: =B65*B60 -> 3239.5
A67: Shortfall to target | B67: =B66-B57 -> 1054.5
A68: MINIMUM COMMON EQUITY RAISE REQUIRED | B68: =MAX(0,B67) -> 1054.5 | F68: Nil if the pro forma ratio already clears the 11.0% target
A69: Issue price ($/share) | B69: ='Cover & Assumptions'!$B$23 -> 44 | F69: Issuance at the current market price; no underwriting discount modelled
A70: New shares issued (mm) | B70: =B68/B69 -> 23.965909
A71: Existing shares outstanding (mm) | B71: ='Cover & Assumptions'!$B$24 -> 120
A72: Pro forma shares outstanding (mm) | B72: =B71+B70 -> 143.96591
A73: Ownership dilution to existing shareholders | B73: =B70/B72 -> 0.16646933
A74: Raise as % of Meridian market capitalisation | B74: =B68/('Cover & Assumptions'!$B$24*'Cover & Assumptions'!$B$23) -> 0.19971591 | F74: The execution-risk gauge for the issuance itself
A76: Pro forma CET1 capital — AFTER equity raise | B76: =B57+B68 -> 3239.5
A77: PRO FORMA CET1 RATIO — after equity raise | B77: =B76/B60 -> 0.11
A78: Headroom over the 7.0% regulatory minimum, before any raise (bps) | B78: =(B61-'Cover & Assumptions'!$B$22)*10000 -> 41.935484
A79: Memo: pro forma CET1 ratio if goodwill were nil | B79: =B55/B60 -> 0.10356537 | F79: Isolates how much of the capital hit is unavoidable RWA absorption rather than the price paid
A80: Memo: equity raise still required even at a nil-goodwill price | B80: =MAX(0,'Cover & Assumptions'!$B$21*B60-B55) -> 189.5 | F80: The floor on the raise, set by RWA alone — no purchase price can go below it
A81: Memo: share of consideration that would have to be STOCK to hold 11.0% without a separate raise | B81: =MIN(1,B68/B11) -> 0.63909091 | F81: Newly issued acquirer stock counts as CET1 and offsets the goodwill deduction
A83: E. THREE-YEAR PRO FORMA INCOME STATEMENT ($mm)
A84: Line item | B84: FY2026E Year 1 | C84: FY2027E Year 2 | D84: FY2028E Year 3 | F84: Note
A85: Bank A standalone contribution
A86: Total revenue | B86: ='Standalone Summary'!$C$119 -> 1498.53 | C86: ='Standalone Summary'!$D$119 -> 1565.9639 | D86: ='Standalone Summary'!$E$119 -> 1636.4322
A87: Provision for credit losses | B87: =-'Standalone Summary'!$C$120 -> -100.8 | C87: =-'Standalone Summary'!$D$120 -> -105.84 | D87: =-'Standalone Summary'!$E$120 -> -111.132
A88: Non-interest expense | B88: =-'Standalone Summary'!$C$121 -> -807.3 | C88: =-'Standalone Summary'!$D$121 -> -835.5555 | D88: =-'Standalone Summary'!$E$121 -> -864.79994
A89: Bank A pre-tax income | B89: =SUM(B86:B88) -> 590.43 | C89: =SUM(C86:C88) -> 624.56835 | D89: =SUM(D86:D88) -> 660.50028
A90: Northfield Card Bank contribution (standalone basis, before synergies)
A91: Total revenue | B91: ='Standalone Summary'!$C$132 -> 1645.6 | C91: ='Standalone Summary'!$D$132 -> 1810.16 | D91: ='Standalone Summary'!$E$132 -> 1991.176
A92: Provision for credit losses | B92: =-'Standalone Summary'!$C$133 -> -442.75 | C92: =-'Standalone Summary'!$D$133 -> -509.1625 | D92: =-'Standalone Summary'!$E$133 -> -585.53688
A93: Non-interest expense | B93: =-'Standalone Summary'!$C$134 -> -678.4 | C93: =-'Standalone Summary'!$D$134 -> -719.104 | D93: =-'Standalone Summary'!$E$134 -> -762.25024
A94: Northfield Card Bank pre-tax income | B94: =SUM(B91:B93) -> 524.45 | C94: =SUM(C91:C93) -> 581.8935 | D94: =SUM(D91:D93) -> 643.38889
A95: Combined pre-tax income before deal effects | B95: =B89+B94 -> 1114.88 | C95: =C89+C94 -> 1206.4618 | D95: =D89+D94 -> 1303.8892
A96: Deal effects
A97: Cost synergies realised | B97: ='Cover & Assumptions'!$B$49*'Cover & Assumptions'!$B$50 -> 76.8 | C97: ='Cover & Assumptions'!$B$49*'Cover & Assumptions'!$B$51 -> 153.6 | D97: ='Cover & Assumptions'!$B$49*'Cover & Assumptions'!$B$52 -> 192 | F97: Run-rate multiplied by the phase-in factor
A98: Revenue synergies realised | B98: ='Cover & Assumptions'!$B$59*'Cover & Assumptions'!$B$60 -> 22.75 | C98: ='Cover & Assumptions'!$B$59*'Cover & Assumptions'!$B$61 -> 45.5 | D98: ='Cover & Assumptions'!$B$59*'Cover & Assumptions'!$B$62 -> 45.5
A99: Integration & restructuring costs | B99: =-'Cover & Assumptions'!$B$63 -> -180 | C99: 0 | D99: 0 | F99: Expensed in Year 1
A100: Interest on new acquisition debt | B100: =-'Cover & Assumptions'!$B$45*'Cover & Assumptions'!$B$47 -> -60.6375 | C100: =-'Cover & Assumptions'!$B$45*'Cover & Assumptions'!$B$47 -> -60.6375 | D100: =-'Cover & Assumptions'!$B$45*'Cover & Assumptions'!$B$47 -> -60.6375
A101: Foregone interest on Meridian cash deployed | B101: =-'Cover & Assumptions'!$B$46*'Cover & Assumptions'!$B$25 -> -14.85 | C101: =-'Cover & Assumptions'!$B$46*'Cover & Assumptions'!$B$25 -> -14.85 | D101: =-'Cover & Assumptions'!$B$46*'Cover & Assumptions'!$B$25 -> -14.85 | F101: Opportunity cost of the equity-funded slice of the consideration
A102: Interest earned on new equity proceeds | B102: =$B$68*'Cover & Assumptions'!$B$25 -> 31.635 | C102: =$B$68*'Cover & Assumptions'!$B$25 -> 31.635 | D102: =$B$68*'Cover & Assumptions'!$B$25 -> 31.635 | F102: Proceeds held in liquid assets pending deployment
A103: PRO FORMA PRE-TAX INCOME | B103: =B95+SUM(B97:B102) -> 990.5775 | C103: =C95+SUM(C97:C102) -> 1361.7094 | D103: =D95+SUM(D97:D102) -> 1497.5367
A104: Income tax | B104: =-B103*'Cover & Assumptions'!$B$20 -> -257.55015 | C104: =-C103*'Cover & Assumptions'!$B$20 -> -354.04443 | D104: =-D103*'Cover & Assumptions'!$B$20 -> -389.35953
A105: PRO FORMA NET INCOME | B105: =B103+B104 -> 733.02735 | C105: =C103+C104 -> 1007.6649 | D105: =D103+D104 -> 1108.1771
A107: F. EPS ACCRETION / (DILUTION)
A108: Item | B108: FY2026E | C108: FY2027E | D108: FY2028E | F108: Note
A109: Pro forma shares outstanding (mm) | B109: =$B$72 -> 143.96591 | C109: =$B$72 -> 143.96591 | D109: =$B$72 -> 143.96591 | F109: The existing 120mm plus any shares issued in the capital raise sized above
A110: Pro forma EPS ($) | B110: =B105/B109 -> 5.0916731 | C110: =C105/C109 -> 6.9993301 | D110: =D105/D109 -> 7.6974969
A111: Bank A standalone EPS ($) | B111: ='Standalone Summary'!$C$154 -> 3.640985 | C111: ='Standalone Summary'!$D$154 -> 3.8515048 | D111: ='Standalone Summary'!$E$154 -> 4.0730851
A112: EPS accretion / (dilution) — $ | B112: =B110-B111 -> 1.4506881 | C112: =C110-C111 -> 3.1478253 | D112: =D110-D111 -> 3.6244118
A113: EPS ACCRETION / (DILUTION) — % | B113: =B110/B111-1 -> 0.39843288 | C113: =C110/C111-1 -> 0.8172975 | D113: =D110/D111-1 -> 0.88984436
...

Sheet Deal C Pro Forma
A1: DEAL C PRO FORMA — PROJECT HARBORVIEW
A2: Meridian Trust Bank acquires Harborview Community Bank — all-cash acquisition
A3: Purchase accounting, pro forma balance sheet, capital walk and three-year accretion / dilution ($mm unless noted)
A5: FICTIONAL / SIMULATED DATA — All entities, financial figures, and events in this document are entirely fictional, created for illustrative/educational simulation purposes. They do not represent any real institution, and nothing here is financial, investment, or M&A advice.
A9: A. PURCHASE PRICE, VALUATION AND GOODWILL
A10: Item | B10: Amount | F10: Derivation / note
A11: Purchase price (all cash) | B11: ='Cover & Assumptions'!$B$68 -> 1050 | F11: Case spec s.5
A12: Target common equity at close (book) | B12: ='Standalone Summary'!$D$24 -> 800 | F12: Harborview Community Bank FY2025 book equity
A13: Less: Day-1 IFRS 9 provisioning gross-up | B13: =-'Cover & Assumptions'!$B$90 -> -12 | F13: Acquisition-accounting allowance build beyond the allowance already carried
A14: Net identifiable assets acquired | B14: =B12+B13 -> 788
A15: GOODWILL CREATED | B15: =B11-B14 -> 262 | F15: Purchase price less (target book equity less the Day-1 provision build)
A17: Implied price / book (x) | B17: =B11/B12 -> 1.3125
A18: Implied price / FY2025 earnings (x) | B18: =B11/'Standalone Summary'!$D$42 -> 14.189189
A19: Premium to standalone implied value | B19: =B11/'Cover & Assumptions'!$B$69-1 -> 0.19318182 | F19: Standalone value per case spec
A20: FY2025 earnings yield on purchase price | B20: ='Standalone Summary'!$D$42/B11 -> 0.07047619 | F20: Compare against the after-tax cost of the acquisition debt below — the gap is what drives accretion
A21: After-tax cost of acquisition debt | B21: ='Cover & Assumptions'!$B$73*(1-'Cover & Assumptions'!$B$20) -> 0.03589
A22: Spread of earnings yield over after-tax debt cost | B22: =B20-B21 -> 0.03458619
A24: B. SOURCES AND USES OF FUNDS
A25: Item | B25: Amount | C25: % of total | F25: Note
A26: Source: new senior debt | B26: ='Cover & Assumptions'!$B$71 -> 525 | C26: =B26/B28 -> 0.5
A27: Source: Meridian cash / excess capital | B27: ='Cover & Assumptions'!$B$72 -> 525 | C27: =B27/B28 -> 0.5
A28: Total sources | B28: =B26+B27 -> 1050
A29: Use: cash consideration to target shareholders | B29: =B11 -> 1050
A30: Total uses | B30: =B29 -> 1050
A31: Memo: one-time integration cost, expensed in Year 1 (pretax) | B31: ='Cover & Assumptions'!$B$89 -> 95
A33: C. PRO FORMA COMBINED BALANCE SHEET AT CLOSE ($mm)
A34: Line item | B34: Bank A FY2025A | C34: Harborview Community Bank FY2025A | D34: Deal adjustments | E34: Pro forma combined | F34: Adjustment note
A35: Cash & equivalents | B35: ='Standalone Summary'!$B$11 -> 1800 | C35: ='Standalone Summary'!$D$11 -> 520 | D35: =-'Cover & Assumptions'!$B$72+B68 -> -337.5 | E35: =B35+C35+D35 -> 1982.5 | F35: Less the cash consideration funded from Meridian's own funds; plus any new equity proceeds
A36: Investment securities | B36: ='Standalone Summary'!$B$12 -> 6200 | C36: ='Standalone Summary'!$D$12 -> 1650 | D36: 0 | E36: =B36+C36+D36 -> 7850
A37: Residential mortgages | B37: ='Standalone Summary'!$B$13 -> 19500 | C37: ='Standalone Summary'!$D$13 -> 4900 | D37: 0 | E37: =B37+C37+D37 -> 24400
A38: Commercial & business loans | B38: ='Standalone Summary'!$B$14 -> 8400 | C38: ='Standalone Summary'!$D$14 -> 1450 | D38: 0 | E38: =B38+C38+D38 -> 9850
A39: Credit card receivables (net) | B39: ='Standalone Summary'!$B$15 -> 1150 | C39: ='Standalone Summary'!$D$15 -> 340 | D39: =-'Cover & Assumptions'!$B$90 -> -12 | E39: =B39+C39+D39 -> 1478 | F39: Day-1 IFRS 9 provisioning gross-up
A40: Other consumer loans | B40: ='Standalone Summary'!$B$16 -> 2950 | C40: ='Standalone Summary'!$D$16 -> 640 | D40: 0 | E40: =B40+C40+D40 -> 3590
A41: Goodwill created on acquisition | B41: 0 | C41: 0 | D41: =B15 -> 262 | E41: =B41+C41+D41 -> 262 | F41: A straight CET1 deduction — see the capital walk below
A42: Other assets | B42: ='Standalone Summary'!$B$17 -> 1000 | C42: ='Standalone Summary'!$D$17 -> 300 | D42: 0 | E42: =B42+C42+D42 -> 1300
A43: Total assets | B43: =SUM(B35:B42) -> 41000 | C43: =SUM(C35:C42) -> 9800 | D43: =SUM(D35:D42) -> -87.5 | E43: =SUM(E35:E42) -> 50712.5
A45: Total deposits | B45: ='Standalone Summary'!$B$20 -> 32500 | C45: ='Standalone Summary'!$D$20 -> 8200 | D45: 0 | E45: =B45+C45+D45 -> 40700
A46: Wholesale borrowings / securitization debt | B46: ='Standalone Summary'!$B$21 -> 4300 | C46: ='Standalone Summary'!$D$21 -> 550 | D46: ='Cover & Assumptions'!$B$71 -> 525 | E46: =B46+C46+D46 -> 5375 | F46: New senior acquisition debt raised
A47: Other liabilities | B47: ='Standalone Summary'!$B$22 -> 900 | C47: ='Standalone Summary'!$D$22 -> 250 | D47: 0 | E47: =B47+C47+D47 -> 1150
A48: Total liabilities | B48: =SUM(B45:B47) -> 37700 | C48: =SUM(C45:C47) -> 9000 | D48: =SUM(D45:D47) -> 525 | E48: =SUM(E45:E47) -> 47225
A49: Common equity | B49: ='Standalone Summary'!$B$24 -> 3300 | C49: ='Standalone Summary'!$D$24 -> 800 | D49: =-'Standalone Summary'!$D$24+B68 -> -612.5 | E49: =B49+C49+D49 -> 3487.5 | F49: Target equity is eliminated in purchase accounting; acquirer equity is unchanged apart from any new issuance
A50: Total liabilities & equity | E50: =E48+E49 -> 50712.5
A51: Check: pro forma assets less liabilities & equity | E51: =E43-E50 -> 0 | F51: Must be nil
A53: D. PRO FORMA CAPITAL WALK AND EQUITY RAISE SIZING
A54: Item | B54: Amount | F54: Note
A55: Bank A standalone CET1 capital | B55: ='Standalone Summary'!$B$46 -> 3050
A56: Less: goodwill created on acquisition (full CET1 deduction) | B56: =-B15 -> -262 | F56: All-cash structure — no shares are issued, so nothing offsets the deduction
A57: Pro forma CET1 capital — BEFORE any equity raise | B57: =B55+B56 -> 2788
A58: Bank A standalone RWA | B58: ='Standalone Summary'!$B$47 -> 22600
A59: Plus: Harborview Community Bank RWA acquired | B59: ='Standalone Summary'!$D$47 -> 4450
A60: Pro forma combined RWA | B60: =B58+B59 -> 27050
A61: PRO FORMA CET1 RATIO — before equity raise | B61: =B57/B60 -> 0.10306839
A62: Memo: Bank A standalone CET1 ratio, pre-deal | B62: ='Standalone Summary'!$B$48 -> 0.13495575
A63: Change in CET1 ratio versus standalone (bps) | B63: =(B61-B62)*10000 -> -318.8736
A65: Meridian internal CET1 target | B65: ='Cover & Assumptions'!$B$21 -> 0.11
A66: CET1 capital required to hold the target | B66: =B65*B60 -> 2975.5
A67: Shortfall to target | B67: =B66-B57 -> 187.5
A68: MINIMUM COMMON EQUITY RAISE REQUIRED | B68: =MAX(0,B67) -> 187.5 | F68: Nil if the pro forma ratio already clears the 11.0% target
A69: Issue price ($/share) | B69: ='Cover & Assumptions'!$B$23 -> 44 | F69: Issuance at the current market price; no underwriting discount modelled
A70: New shares issued (mm) | B70: =B68/B69 -> 4.2613636
A71: Existing shares outstanding (mm) | B71: ='Cover & Assumptions'!$B$24 -> 120
A72: Pro forma shares outstanding (mm) | B72: =B71+B70 -> 124.26136
A73: Ownership dilution to existing shareholders | B73: =B70/B72 -> 0.034293553
A74: Raise as % of Meridian market capitalisation | B74: =B68/('Cover & Assumptions'!$B$24*'Cover & Assumptions'!$B$23) -> 0.035511364 | F74: The execution-risk gauge for the issuance itself
A76: Pro forma CET1 capital — AFTER equity raise | B76: =B57+B68 -> 2975.5
A77: PRO FORMA CET1 RATIO — after equity raise | B77: =B76/B60 -> 0.11
A78: Headroom over the 7.0% regulatory minimum, before any raise (bps) | B78: =(B61-'Cover & Assumptions'!$B$22)*10000 -> 330.68392
A79: Memo: pro forma CET1 ratio if goodwill were nil | B79: =B55/B60 -> 0.11275416 | F79: Isolates how much of the capital hit is unavoidable RWA absorption rather than the price paid
A80: Memo: equity raise still required even at a nil-goodwill price | B80: =MAX(0,'Cover & Assumptions'!$B$21*B60-B55) -> 0 | F80: The floor on the raise, set by RWA alone — no purchase price can go below it
A81: Memo: share of consideration that would have to be STOCK to hold 11.0% without a separate raise | B81: =MIN(1,B68/B11) -> 0.17857143 | F81: Newly issued acquirer stock counts as CET1 and offsets the goodwill deduction
A83: E. THREE-YEAR PRO FORMA INCOME STATEMENT ($mm)
A84: Line item | B84: FY2026E Year 1 | C84: FY2027E Year 2 | D84: FY2028E Year 3 | F84: Note
A85: Bank A standalone contribution
A86: Total revenue | B86: ='Standalone Summary'!$C$119 -> 1498.53 | C86: ='Standalone Summary'!$D$119 -> 1565.9639 | D86: ='Standalone Summary'!$E$119 -> 1636.4322
A87: Provision for credit losses | B87: =-'Standalone Summary'!$C$120 -> -100.8 | C87: =-'Standalone Summary'!$D$120 -> -105.84 | D87: =-'Standalone Summary'!$E$120 -> -111.132
A88: Non-interest expense | B88: =-'Standalone Summary'!$C$121 -> -807.3 | C88: =-'Standalone Summary'!$D$121 -> -835.5555 | D88: =-'Standalone Summary'!$E$121 -> -864.79994
A89: Bank A pre-tax income | B89: =SUM(B86:B88) -> 590.43 | C89: =SUM(C86:C88) -> 624.56835 | D89: =SUM(D86:D88) -> 660.50028
A90: Harborview Community Bank contribution (standalone basis, before synergies)
A91: Total revenue | B91: ='Standalone Summary'!$C$145 -> 318.27 | C91: ='Standalone Summary'!$D$145 -> 327.8181 | D91: ='Standalone Summary'!$E$145 -> 337.65264
A92: Provision for credit losses | B92: =-'Standalone Summary'!$C$146 -> -14.56 | C92: =-'Standalone Summary'!$D$146 -> -15.1424 | D92: =-'Standalone Summary'!$E$146 -> -15.748096
A93: Non-interest expense | B93: =-'Standalone Summary'!$C$147 -> -200.85 | C93: =-'Standalone Summary'!$D$147 -> -206.8755 | D93: =-'Standalone Summary'!$E$147 -> -213.08176
A94: Harborview Community Bank pre-tax income | B94: =SUM(B91:B93) -> 102.86 | C94: =SUM(C91:C93) -> 105.8002 | D94: =SUM(D91:D93) -> 108.82278
A95: Combined pre-tax income before deal effects | B95: =B89+B94 -> 693.29 | C95: =C89+C94 -> 730.36855 | D95: =D89+D94 -> 769.32306
A96: Deal effects
A97: Cost synergies realised | B97: ='Cover & Assumptions'!$B$75*'Cover & Assumptions'!$B$76 -> 43.875 | C97: ='Cover & Assumptions'!$B$75*'Cover & Assumptions'!$B$77 -> 74.5875 | D97: ='Cover & Assumptions'!$B$75*'Cover & Assumptions'!$B$78 -> 87.75 | F97: Run-rate multiplied by the phase-in factor
A98: Revenue synergies realised | B98: ='Cover & Assumptions'!$B$85*'Cover & Assumptions'!$B$86 -> 28.90625 | C98: ='Cover & Assumptions'!$B$85*'Cover & Assumptions'!$B$87 -> 57.8125 | D98: ='Cover & Assumptions'!$B$85*'Cover & Assumptions'!$B$88 -> 57.8125
A99: Integration & restructuring costs | B99: =-'Cover & Assumptions'!$B$89 -> -95 | C99: 0 | D99: 0 | F99: Expensed in Year 1
A100: Interest on new acquisition debt | B100: =-'Cover & Assumptions'!$B$71*'Cover & Assumptions'!$B$73 -> -25.4625 | C100: =-'Cover & Assumptions'!$B$71*'Cover & Assumptions'!$B$73 -> -25.4625 | D100: =-'Cover & Assumptions'!$B$71*'Cover & Assumptions'!$B$73 -> -25.4625
A101: Foregone interest on Meridian cash deployed | B101: =-'Cover & Assumptions'!$B$72*'Cover & Assumptions'!$B$25 -> -15.75 | C101: =-'Cover & Assumptions'!$B$72*'Cover & Assumptions'!$B$25 -> -15.75 | D101: =-'Cover & Assumptions'!$B$72*'Cover & Assumptions'!$B$25 -> -15.75 | F101: Opportunity cost of the equity-funded slice of the consideration
A102: Interest earned on new equity proceeds | B102: =$B$68*'Cover & Assumptions'!$B$25 -> 5.625 | C102: =$B$68*'Cover & Assumptions'!$B$25 -> 5.625 | D102: =$B$68*'Cover & Assumptions'!$B$25 -> 5.625 | F102: Proceeds held in liquid assets pending deployment
A103: PRO FORMA PRE-TAX INCOME | B103: =B95+SUM(B97:B102) -> 635.48375 | C103: =C95+SUM(C97:C102) -> 827.18105 | D103: =D95+SUM(D97:D102) -> 879.29806
A104: Income tax | B104: =-B103*'Cover & Assumptions'!$B$20 -> -165.22577 | C104: =-C103*'Cover & Assumptions'!$B$20 -> -215.06707 | D104: =-D103*'Cover & Assumptions'!$B$20 -> -228.6175
A105: PRO FORMA NET INCOME | B105: =B103+B104 -> 470.25797 | C105: =C103+C104 -> 612.11398 | D105: =D103+D104 -> 650.68057
A107: F. EPS ACCRETION / (DILUTION)
A108: Item | B108: FY2026E | C108: FY2027E | D108: FY2028E | F108: Note
A109: Pro forma shares outstanding (mm) | B109: =$B$72 -> 124.26136 | C109: =$B$72 -> 124.26136 | D109: =$B$72 -> 124.26136 | F109: The existing 120mm plus any shares issued in the capital raise sized above
A110: Pro forma EPS ($) | B110: =B105/B109 -> 3.7844263 | C110: =C105/C109 -> 4.9260201 | D110: =D105/D109 -> 5.2363868
A111: Bank A standalone EPS ($) | B111: ='Standalone Summary'!$C$154 -> 3.640985 | C111: ='Standalone Summary'!$D$154 -> 3.8515048 | D111: ='Standalone Summary'!$E$154 -> 4.0730851
A112: EPS accretion / (dilution) — $ | B112: =B110-B111 -> 0.14344132 | C112: =C110-C111 -> 1.0745153 | D112: =D110-D111 -> 1.1633018
A113: EPS ACCRETION / (DILUTION) — % | B113: =B110/B111-1 -> 0.039396295 | C113: =C110/C111-1 -> 0.27898584 | D113: =D110/D111-1 -> 0.28560704
...

Sheet Side-by-Side
A1: SIDE-BY-SIDE COMPARISON — DEAL B versus DEAL C
A2: Every figure below is a live link to the Deal B and Deal C pro forma sheets
A3: CAD $ millions unless noted. 'Favours' marks which deal the metric argues for.
A5: FICTIONAL / SIMULATED DATA — All entities, financial figures, and events in this document are entirely fictional, created for illustrative/educational simulation purposes. They do not represent any real institution, and nothing here is financial, investment, or M&A advice.
A9: TRANSACTION TERMS
A10: Metric | B10: Deal B Northfield Card | C10: Deal C Harborview Comm. | D10: Favours | E10: Comment
A11: Purchase price ($mm) | B11: ='Deal B Pro Forma'!$B$11 -> 1650 | C11: ='Deal C Pro Forma'!$B$11 -> 1050
A12: Implied price / book (x) | B12: ='Deal B Pro Forma'!$B$17 -> 1.8333333 | C12: ='Deal C Pro Forma'!$B$17 -> 1.3125 | E12: Northfield is priced at a far higher multiple of book
A13: Implied price / FY2025 earnings (x) | B13: ='Deal B Pro Forma'!$B$18 -> 4.7340334 | C13: ='Deal C Pro Forma'!$B$18 -> 14.189189 | E13: But far cheaper on earnings — Northfield runs a 38.8% ROE
A14: Premium to standalone implied value | B14: ='Deal B Pro Forma'!$B$19 -> 0.25 | C14: ='Deal C Pro Forma'!$B$19 -> 0.19318182
A15: New senior acquisition debt ($mm) | B15: ='Deal B Pro Forma'!$B$26 -> 1155 | C15: ='Deal C Pro Forma'!$B$26 -> 525
A16: Meridian cash / excess capital deployed ($mm) | B16: ='Deal B Pro Forma'!$B$27 -> 495 | C16: ='Deal C Pro Forma'!$B$27 -> 525
A17: Day-1 IFRS 9 provisioning gross-up ($mm) | B17: ='Cover & Assumptions'!$B$64 -> 115 | C17: ='Cover & Assumptions'!$B$90 -> 12
A18: GOODWILL CREATED ($mm) | B18: ='Deal B Pro Forma'!$B$15 -> 865 | C18: ='Deal C Pro Forma'!$B$15 -> 262 | D18: Deal C | E18: Deducted from CET1 in full — this is the capital cost of the premium
A19: One-time integration cost ($mm pretax) | B19: ='Deal B Pro Forma'!$B$31 -> 180 | C19: ='Deal C Pro Forma'!$B$31 -> 95
A20: Earnings yield on purchase price less after-tax debt cost | B20: ='Deal B Pro Forma'!$B$22 -> 0.17238636 | C20: ='Deal C Pro Forma'!$B$22 -> 0.03458619 | D20: Deal B | E20: The arithmetic source of accretion in a debt-funded cash deal
A22: SCALE AND STRATEGIC IMPACT
A23: Metric | B23: Deal B | C23: Deal C | D23: Favours | E23: Comment
A24: Target total assets ($mm) | B24: ='Standalone Summary'!$C$18 -> 10400 | C24: ='Standalone Summary'!$D$18 -> 9800
A25: Target gross card receivables ($mm) | B25: ='Standalone Summary'!$C$56 -> 7550 | C25: ='Standalone Summary'!$D$56 -> 355 | D25: Deal B | E25: Meridian's own book is only 1,190
A26: Combined gross card receivables ($mm) | B26: ='Standalone Summary'!$B$56+'Standalone Summary'!$C$56 -> 8740 | C26: ='Standalone Summary'!$B$56+'Standalone Summary'!$D$56 -> 1545 | D26: Deal B
A27: Uplift to Meridian's card book (x) | B27: =B26/'Standalone Summary'!$B$56 -> 7.3445378 | C27: =C26/'Standalone Summary'!$B$56 -> 1.2983193 | D27: Deal B | E27: The core strategic test: does the deal actually scale card lending?
A28: Target active card accounts (000s) | B28: ='Standalone Summary'!$C$55 -> 2850 | C28: ='Standalone Summary'!$D$55 -> 145 | D28: Deal B
A29: Target annual card purchase volume ($mm) | B29: ='Standalone Summary'!$C$65 -> 15300 | C29: ='Standalone Summary'!$D$65 -> 1350 | D29: Deal B
A30: Target posted APR | B30: ='Standalone Summary'!$C$66 -> 0.2299 | C30: ='Standalone Summary'!$D$66 -> 0.1999 | D30: Deal B
A31: Target revolve rate | B31: ='Standalone Summary'!$C$61 -> 0.71 | C31: ='Standalone Summary'!$D$61 -> 0.35 | E31: High revolve means high yield AND high adverse selection — the same fact cuts both ways
A32: Target committed but undrawn card lines ($mm) | B32: ='Standalone Summary'!$C$64 -> 12350 | C32: ='Standalone Summary'!$D$64 -> 1425 | D32: Deal C | E32: Contingent exposure acquired — the drawdown option the borrower holds
A33: Target deposits acquired ($mm) | B33: ='Standalone Summary'!$C$20 -> 6100 | C33: ='Standalone Summary'!$D$20 -> 8200 | D33: Deal C | E33: Harborview's are branch-sourced chequing/savings; Northfield's are broker and direct-to-consumer
A35: CAPITAL IMPACT
A36: Metric | B36: Deal B | C36: Deal C | D36: Favours | E36: Comment
A37: Pro forma combined RWA ($mm) | B37: ='Deal B Pro Forma'!$B$60 -> 29450 | C37: ='Deal C Pro Forma'!$B$60 -> 27050
A38: PRO FORMA CET1 RATIO — before equity raise | B38: ='Deal B Pro Forma'!$B$61 -> 0.074193548 | C38: ='Deal C Pro Forma'!$B$61 -> 0.10306839 | D38: Deal C | E38: Meridian standalone is 13.50%; the internal target is 11.00%
A39: Change versus standalone CET1 (bps) | B39: ='Deal B Pro Forma'!$B$63 -> -607.62204 | C39: ='Deal C Pro Forma'!$B$63 -> -318.8736 | D39: Deal C
A40: Headroom over the 7.0% regulatory minimum, before raise (bps) | B40: ='Deal B Pro Forma'!$B$78 -> 41.935484 | C40: ='Deal C Pro Forma'!$B$78 -> 330.68392 | D40: Deal C
A41: MINIMUM EQUITY RAISE TO RESTORE THE 11.0% TARGET ($mm) | B41: ='Deal B Pro Forma'!$B$68 -> 1054.5 | C41: ='Deal C Pro Forma'!$B$68 -> 187.5 | D41: Deal C | E41: The decisive capital number in this decision
A42: Raise as % of Meridian market capitalisation | B42: ='Deal B Pro Forma'!$B$74 -> 0.19971591 | C42: ='Deal C Pro Forma'!$B$74 -> 0.035511364 | D42: Deal C | E42: Equity-issuance execution risk
A43: New shares issued (mm) | B43: ='Deal B Pro Forma'!$B$70 -> 23.965909 | C43: ='Deal C Pro Forma'!$B$70 -> 4.2613636 | D43: Deal C
A44: Ownership dilution to existing shareholders | B44: ='Deal B Pro Forma'!$B$73 -> 0.16646933 | C44: ='Deal C Pro Forma'!$B$73 -> 0.034293553 | D44: Deal C
A45: Pro forma CET1 ratio — after equity raise | B45: ='Deal B Pro Forma'!$B$77 -> 0.11 | C45: ='Deal C Pro Forma'!$B$77 -> 0.11
A46: Memo: pro forma CET1 ratio if goodwill were nil | B46: ='Deal B Pro Forma'!$B$79 -> 0.10356537 | C46: ='Deal C Pro Forma'!$B$79 -> 0.11275416 | E46: Shows how much of the hit is unavoidable RWA absorption rather than the price paid
A47: Memo: equity raise still required even at a nil-goodwill price ($mm) | B47: ='Deal B Pro Forma'!$B$80 -> 189.5 | C47: ='Deal C Pro Forma'!$B$80 -> 0 | E47: For Deal B this floor is positive — no achievable price clears the target without new capital
A48: Memo: stock consideration needed to self-fund the deal | B48: ='Deal B Pro Forma'!$B$81 -> 0.63909091 | C48: ='Deal C Pro Forma'!$B$81 -> 0.17857143 | E48: The all-cash structure is precisely what forces the separate raise
A49: Tangible book value per share accretion / (dilution) | B49: ='Deal B Pro Forma'!$B$122 -> -0.11468112 | C49: ='Deal C Pro Forma'!$B$122 -> -0.05788212 | D49: Deal C
A51: EARNINGS AND RETURNS
A52: Metric | B52: Deal B | C52: Deal C | D52: Favours | E52: Comment
A53: Cost synergies run-rate ($mm) | B53: ='Cover & Assumptions'!$B$49 -> 192 | C53: ='Cover & Assumptions'!$B$75 -> 87.75
A54: Revenue synergies run-rate ($mm) | B54: ='Cover & Assumptions'!$B$59 -> 45.5 | C54: ='Cover & Assumptions'!$B$85 -> 57.8125
A55: Pro forma net income — FY2026E ($mm) | B55: ='Deal B Pro Forma'!$B$105 -> 733.02735 | C55: ='Deal C Pro Forma'!$B$105 -> 470.25797
A56: Pro forma net income — FY2028E ($mm) | B56: ='Deal B Pro Forma'!$D$105 -> 1108.1771 | C56: ='Deal C Pro Forma'!$D$105 -> 650.68057
A57: Pro forma EPS — FY2026E ($) | B57: ='Deal B Pro Forma'!$B$110 -> 5.0916731 | C57: ='Deal C Pro Forma'!$B$110 -> 3.7844263
A58: Pro forma EPS — FY2028E ($) | B58: ='Deal B Pro Forma'!$D$110 -> 7.6974969 | C58: ='Deal C Pro Forma'!$D$110 -> 5.2363868
A59: EPS accretion / (dilution) — Year 1 | B59: ='Deal B Pro Forma'!$B$113 -> 0.39843288 | C59: ='Deal C Pro Forma'!$B$113 -> 0.039396295 | D59: Deal B
A60: EPS accretion / (dilution) — Year 2 | B60: ='Deal B Pro Forma'!$C$113 -> 0.8172975 | C60: ='Deal C Pro Forma'!$C$113 -> 0.27898584 | D60: Deal B
A61: EPS ACCRETION / (DILUTION) — YEAR 3 | B61: ='Deal B Pro Forma'!$D$113 -> 0.88984436 | C61: ='Deal C Pro Forma'!$D$113 -> 0.28560704 | D61: Deal B
A62: Year-3 ROIC on purchase price plus integration | B62: ='Deal B Pro Forma'!$D$130 -> 0.36555506 | C62: ='Deal C Pro Forma'!$D$130 -> 0.16803098 | D62: Deal B
A63: Year-3 ROIC on TOTAL capital committed | B63: ='Deal B Pro Forma'!$D$131 -> 0.22971342 | C63: ='Deal C Pro Forma'!$D$131 -> 0.14394029 | D63: Deal B | E63: Includes the equity raise the deal forces
A64: Three-year deal IRR | B64: ='Deal B Pro Forma'!$B$133 -> 0.54521768 | C64: ='Deal C Pro Forma'!$B$133 -> 0.30370923 | D64: Deal B
A66: CREDIT AND CONDUCT RISK OF THE ACQUIRED BOOK
A67: Metric | B67: Deal B | C67: Deal C | D67: Favours | E67: Comment
A68: Net charge-off rate — FY2025 | B68: ='Standalone Summary'!$C$69 -> 0.046 | C68: ='Standalone Summary'!$D$69 -> 0.012 | D68: Deal C
A69: Net charge-off rate — FY2023 | B69: ='Standalone Summary'!$B$103 -> 0.03 | C69: ='Standalone Summary'!$B$108 -> 0.012
A70: 90+ DPD — FY2025 | B70: ='Standalone Summary'!$C$68 -> 0.024 | C70: ='Standalone Summary'!$D$68 -> 0.005 | D70: Deal C
A71: 90+ DPD — FY2023 | B71: ='Standalone Summary'!$B$102 -> 0.015 | C71: ='Standalone Summary'!$B$107 -> 0.005
A72: THREE-YEAR CHANGE IN 90+ DPD (bps) | B72: =('Standalone Summary'!$C$68-'Standalone Summary'!$B$102)*10000 -> 90 | C72: =('Standalone Summary'!$D$68-'Standalone Summary'!$B$107)*10000 -> 0 | D72: Deal C | E72: Northfield's credit quality deteriorated while it grew; Harborview's did not move
A73: Three-year change in net charge-off rate (bps) | B73: =('Standalone Summary'!$C$69-'Standalone Summary'!$B$103)*10000 -> 160 | C73: =('Standalone Summary'!$D$69-'Standalone Summary'!$B$108)*10000 -> 0 | D73: Deal C
A74: Three-year change in CET1 ratio (bps) | B74: =('Standalone Summary'!$C$48-'Standalone Summary'!$B$104)*10000 -> -196.71533 | C74: =('Standalone Summary'!$D$48-'Standalone Summary'!$B$109)*10000 -> 57.865169 | D74: Deal C | E74: Northfield was already running out of capital before the deal was contemplated
A75: Blended 12-month PD | B75: ='Standalone Summary'!$C$73 -> 0.054 | C75: ='Standalone Summary'!$D$73 -> 0.014 | D75: Deal C
A76: Loss given default | B76: ='Standalone Summary'!$C$74 -> 0.86 | C76: ='Standalone Summary'!$D$74 -> 0.78 | D76: Deal C
A77: Expected loss rate (PD x LGD) | B77: ='Standalone Summary'!$C$73*'Standalone Summary'!$C$74 -> 0.04644 | C77: ='Standalone Summary'!$D$73*'Standalone Summary'!$D$74 -> 0.01092 | D77: Deal C
A78: IFRS 9 Stage 3 (% of gross) | B78: ='Standalone Summary'!$C$72 -> 0.065 | C78: ='Standalone Summary'!$D$72 -> 0.01 | D78: Deal C
A79: IFRS 9 Stage 2 (% of gross) | B79: ='Standalone Summary'!$C$71 -> 0.125 | C79: ='Standalone Summary'!$D$71 -> 0.04 | D79: Deal C | E79: Stage 2 is the leading indicator — balances already flagged for a significant increase in credit risk
A80: Allowance coverage of gross receivables | B80: ='Standalone Summary'!$C$59 -> 0.046357616 | C80: ='Standalone Summary'!$D$59 -> 0.042253521
A81: Integration cost as % of purchase price | B81: ='Cover & Assumptions'!$B$63/'Cover & Assumptions'!$B$42 -> 0.10909091 | C81: ='Cover & Assumptions'!$B$89/'Cover & Assumptions'!$B$68 -> 0.09047619 | D81: Deal C
A82: Open conduct-regulator matter | B82: Yes — 2024 CLI consent / affordability remediation | C82: None | D82: Deal C | E82: Case spec s.3 records the Northfield matter as closed via remediation but not fully retired

Sheet Decision Scorecard
A1: DECISION SCORECARD — WEIGHTED EVALUATION
A2: Framework per case spec section 6. Scores run 1 (poor) to 5 (excellent).
A3: Every score is anchored to a computed figure reproduced in the evidence block below — nothing here is asserted without a number behind it.
A5: FICTIONAL / SIMULATED DATA — All entities, financial figures, and events in this document are entirely fictional, created for illustrative/educational simulation purposes. They do not represent any real institution, and nothing here is financial, investment, or M&A advice.
A9: A. EVIDENCE BASE — THE COMPUTED NUMBERS BEHIND EACH SCORE
A10: Evidence metric | B10: Deal B | C10: Deal C | G10: Source tab
A11: Uplift to combined card receivables (x) | B11: ='Side-by-Side'!$B$27 -> 7.3445378 | C11: ='Side-by-Side'!$C$27 -> 1.2983193 | G11: Side-by-Side
A12: Card accounts acquired (000s) | B12: ='Standalone Summary'!$C$55 -> 2850 | C12: ='Standalone Summary'!$D$55 -> 145 | G12: Standalone Summary
A13: Year-3 EPS accretion / (dilution) | B13: ='Deal B Pro Forma'!$D$113 -> 0.88984436 | C13: ='Deal C Pro Forma'!$D$113 -> 0.28560704 | G13: Deal pro forma tabs
A14: Year-3 ROIC on total capital committed | B14: ='Deal B Pro Forma'!$D$131 -> 0.22971342 | C14: ='Deal C Pro Forma'!$D$131 -> 0.14394029 | G14: Deal pro forma tabs
A15: Pro forma CET1 ratio before any raise | B15: ='Deal B Pro Forma'!$B$61 -> 0.074193548 | C15: ='Deal C Pro Forma'!$B$61 -> 0.10306839 | G15: Deal pro forma tabs
A16: Equity raise required ($mm) | B16: ='Deal B Pro Forma'!$B$68 -> 1054.5 | C16: ='Deal C Pro Forma'!$B$68 -> 187.5 | G16: Deal pro forma tabs
A17: Equity raise as % of market capitalisation | B17: ='Deal B Pro Forma'!$B$74 -> 0.19971591 | C17: ='Deal C Pro Forma'!$B$74 -> 0.035511364 | G17: Deal pro forma tabs
A18: Acquired book net charge-off rate | B18: ='Standalone Summary'!$C$69 -> 0.046 | C18: ='Standalone Summary'!$D$69 -> 0.012 | G18: Standalone Summary
A19: Three-year change in acquired book 90+ DPD (bps) | B19: =('Standalone Summary'!$C$68-'Standalone Summary'!$B$102)*10000 -> 90 | C19: =('Standalone Summary'!$D$68-'Standalone Summary'!$B$107)*10000 -> 0 | G19: Standalone Summary trend block
A20: Acquired book expected loss rate (PD x LGD) | B20: ='Standalone Summary'!$C$73*'Standalone Summary'!$C$74 -> 0.04644 | C20: ='Standalone Summary'!$D$73*'Standalone Summary'!$D$74 -> 0.01092 | G20: Standalone Summary
A21: Integration cost as % of purchase price | B21: ='Cover & Assumptions'!$B$63/'Cover & Assumptions'!$B$42 -> 0.10909091 | C21: ='Cover & Assumptions'!$B$89/'Cover & Assumptions'!$B$68 -> 0.09047619 | G21: Cover & Assumptions
A23: B. WEIGHTED SCORECARD
A24: Dimension | B24: Weight | C24: Bank B score | D24: Bank C score | E24: Bank B weighted | F24: Bank C weighted | G24: Basis for the score (evidence-linked)
A25: Strategic fit / scale impact on the card lending goal | B25: 0.2 | C25: 5 | D25: 2 | E25: =$B$25*C25 -> 1 | F25: =$B$25*D25 -> 0.4 | G25: Deal B multiplies the combined card book about 7.3x and adds 2.85mm accounts at a 22.99% APR — it delivers the board's mandate in a single step. Deal C lifts the book only about 1.3x; it brings a clean underwriting model and a low-cost deposit base, but it does not scale card lending.
A26: Financial accretion (EPS accretion / dilution by Year 3) | B26: 0.2 | C26: 5 | D26: 4 | E26: =$B$26*C26 -> 1 | F26: =$B$26*D26 -> 0.8 | G26: Both deals are accretive. Deal B is far more so, because a 38.8% ROE book bought at roughly 4.7x earnings and 70% debt-funded is arithmetically powerful. Deal C's accretion is solid but leans heavily on the 10bps blended funding synergy, which is the single largest diligence item on that side.
A27: Risk-adjusted return (deal IRR / NPV net of credit risk) | B27: 0.2 | C27: 3 | D27: 4 | E27: =$B$27*C27 -> 0.6 | F27: =$B$27*D27 -> 0.8 | G27: In the base case Deal B's ROIC on committed capital is well ahead. Under the section-7 recession stress the two converge to within a few tens of basis points (see Stress Test, section F) — Deal B's excess return is a credit-risk premium rather than durable alpha, and its variance is several times Deal C's.
A28: Capital impact (pro forma CET1, equity raise need) | B28: 0.15 | C28: 1 | D28: 4 | E28: =$B$28*C28 -> 0.15 | F28: =$B$28*D28 -> 0.6 | G28: Deal B takes pro forma CET1 to about 7.4% — some 358bps below the internal target and barely above the 7.0% regulatory floor — forcing a raise of roughly $1.05bn, about 20% of market capitalisation. Deal C dips about 69bps below target and can be self-cured out of retained earnings within roughly two quarters.
A29: Credit / asset quality risk (delinquency trend, PD/LGD, provisioning volatility) | B29: 0.15 | C29: 1 | D29: 5 | E29: =$B$29*C29 -> 0.15 | F29: =$B$29*D29 -> 0.75 | G29: Northfield: NCO 4.6% and rising, 90+ DPD 2.4% (up 90bps in three years), PD 5.4%, LGD 86%, Stage 3 6.5%, plus 12,350 of undrawn lines. Harborview: NCO 1.2% flat, 90+ DPD 0.5% flat, PD 1.4%, LGD 78%, Stage 3 1.0%.
A30: Regulatory / conduct and integration risk | B30: 0.1 | C30: 1 | D30: 5 | E30: =$B$30*C30 -> 0.1 | F30: =$B$30*D30 -> 0.5 | G30: Northfield carries an unretired 2024 CLI consent and affordability remediation, plus a $180mm integration bill (10.9% of price) covering both technology and compliance. Harborview is a clean branch and back-office overlap at $95mm (9.0% of price).
A31: WEIGHTED TOTAL | B31: =SUM(B25:B30) -> 1 | E31: =SUM(E25:E30) -> 3 | F31: =SUM(F25:F30) -> 3.85
A32: Cross-check via SUMPRODUCT | E32: =SUMPRODUCT($B$25:$B$30,C25:C30) -> 3 | F32: =SUMPRODUCT($B$25:$B$30,D25:D30) -> 3.85
A33: SCORECARD WINNER | E33: =IF(E31>F31,"DEAL B — NORTHFIELD",IF(F31>E31,"DEAL C — HARBORVIEW","TIE")) -> DEAL C — HARBORVIEW
A34: Weighted-score margin | E34: =ABS(E31-F31) -> 0.85
A36: C. IS THE CONCLUSION SENSITIVE TO A SINGLE JUDGEMENT CALL?
A37: Test | B37: Deal B | C37: Deal C | D37: Result | G37: Comment
A38: Weighted score on the two GROWTH dimensions only (strategic fit + accretion) | C38: =E25+E26 -> 2 | D38: =F25+F26 -> 1.2 | E38: =IF(C38>D38,"Deal B wins","Deal C wins") -> Deal B wins
A39: Weighted score on the four RISK dimensions only (risk-adj. return, capital, credit, conduct) | C39: =E27+E28+E29+E30 -> 1 | D39: =F27+F28+F29+F30 -> 2.65 | E39: =IF(C39>D39,"Deal B wins","Deal C wins") -> Deal C wins
A40: Break-even: the capital-impact score Deal B would need to draw level overall | C40: =C28+(F31-E31)/$B$28 -> 6.6666667 | G40: Compare against the maximum possible score of 5
A41: Break-even: the credit-risk score Deal B would need to draw level overall | C41: =C29+(F31-E31)/$B$29 -> 6.6666667 | G41: Compare against the maximum possible score of 5
A42: Even scoring Deal B a perfect 5 on capital impact — which the computed 7.4% pro forma CET1 flatly contradicts — would not overturn the result on these weights. The conclusion does not rest on any single judgement call.

Sheet Stress Test
A1: STRESS TEST — RECESSION SCENARIO (case spec section 7)
A2: Card NCO +200bps and 90+ DPD +150bps on the acquired portfolios; +50bps NCO on Meridian's existing prime book
A3: Stress year modelled: FY2026E, Year 1 post-close and the most binding point for pro forma capital. $mm unless noted.
A5: FICTIONAL / SIMULATED DATA — All entities, financial figures, and events in this document are entirely fictional, created for illustrative/educational simulation purposes. They do not represent any real institution, and nothing here is financial, investment, or M&A advice.
A9: A. STRESS PARAMETERS
A10: Parameter | B10: Value | E10: Source
A11: Net charge-off uplift — acquired card portfolios | B11: ='Cover & Assumptions'!$B$94 -> 0.02 | E11: Case spec s.7
A12: 90+ DPD uplift — acquired card portfolios | B12: ='Cover & Assumptions'!$B$95 -> 0.015 | E12: Case spec s.7
A13: Net charge-off uplift — Meridian's existing card book | B13: ='Cover & Assumptions'!$B$96 -> 0.005 | E13: Case spec s.7 — prime and transactor-heavy, so it flexes less
A14: EAD migration — share of undrawn lines drawn under stress | B14: ='Cover & Assumptions'!$B$97 -> 0.05 | E14: Model overlay: distressed borrowers draw before they default
A15: Mechanics. The charge-off uplift flows straight to provision expense. The 90+ DPD uplift moves balances into IFRS 9 Stage 3, where the allowance is a lifetime expected credit loss — modelled as the migrated balance multiplied by the book's own LGD. The EAD overlay converts undrawn commitments carried at a 10% CCF into on-balance-sheet exposure at a 75% risk weight.
A17: B. INCREMENTAL PROVISION EXPENSE UNDER STRESS (FY2026E)
A18: Component | B18: Deal B | C18: Deal C | E18: Calculation
A19: Acquired book gross card receivables — FY2026E | B19: ='Standalone Summary'!$C$137 -> 8305 | C19: ='Standalone Summary'!$C$150 -> 369.2
A20: Acquired book LGD | B20: ='Standalone Summary'!$C$74 -> 0.86 | C20: ='Standalone Summary'!$D$74 -> 0.78
A21: Incremental charge-offs on the acquired book | B21: =B19*'Cover & Assumptions'!$B$94 -> 166.1 | C21: =C19*'Cover & Assumptions'!$B$94 -> 7.384 | E21: gross receivables x +200bps
A22: Stage 3 migration — lifetime ECL build on the acquired book | B22: =B19*'Cover & Assumptions'!$B$95*B20 -> 107.1345 | C22: =C19*'Cover & Assumptions'!$B$95*C20 -> 4.31964 | E22: gross receivables x +150bps x LGD
A23: Meridian existing gross card receivables — FY2026E | B23: ='Standalone Summary'!$C$124 -> 1261.4 | C23: ='Standalone Summary'!$C$124 -> 1261.4
A24: Incremental charge-offs on Meridian's existing book | B24: =B23*'Cover & Assumptions'!$B$96 -> 6.307 | C24: =C23*'Cover & Assumptions'!$B$96 -> 6.307 | E24: gross receivables x +50bps
A25: TOTAL INCREMENTAL PROVISION EXPENSE (pretax) | B25: =B21+B22+B24 -> 279.5415 | C25: =C21+C22+C24 -> 18.01064
A26: After-tax impact on capital | B26: =B25*(1-'Cover & Assumptions'!$B$20) -> 206.86071 | C26: =C25*(1-'Cover & Assumptions'!$B$20) -> 13.327874
A27: Stress provision as a multiple of the deal's base-case Year-1 provision | B27: =B25/('Standalone Summary'!$C$120+'Standalone Summary'!$C$133) -> 0.51428847 | C27: =C25/('Standalone Summary'!$C$120+'Standalone Summary'!$C$146) -> 0.15612552
A29: C. EAD MIGRATION OVERLAY — RWA IMPACT
A30: Component | B30: Deal B | C30: Deal C | E30: Calculation
A31: Acquired book undrawn card lines — FY2026E | B31: ='Standalone Summary'!$C$138 -> 13585 | C31: ='Standalone Summary'!$C$151 -> 1482
A32: Undrawn balances drawn under stress | B32: =B31*'Cover & Assumptions'!$B$97 -> 679.25 | C32: =C31*'Cover & Assumptions'!$B$97 -> 74.1
A33: Incremental RWA (on balance sheet at 75% RW, less the 10% CCF already capitalised) | B33: =B32*('Cover & Assumptions'!$B$28-'Cover & Assumptions'!$B$27*'Cover & Assumptions'!$B$28) -> 458.49375 | C33: =C32*('Cover & Assumptions'!$B$28-'Cover & Assumptions'!$B$27*'Cover & Assumptions'!$B$28) -> 50.0175
A34: This is the option asymmetry at portfolio scale. The customer's drawdown right is exercised precisely when the bank would most like to cancel, and the regulatory 10% conversion factor capitalises only a tenth of the committed exposure until it converts. Buying Northfield means buying 12,350 of these options at once.
A36: D. STRESSED PRO FORMA CAPITAL
A37: Item | B37: Deal B | C37: Deal C | E37: Note
A38: Pro forma CET1 capital after the equity raise (base case) | B38: ='Deal B Pro Forma'!$B$76 -> 3239.5 | C38: ='Deal C Pro Forma'!$B$76 -> 2975.5
A39: Less: after-tax stress provision | B39: =-B26 -> -206.86071 | C39: =-C26 -> -13.327874
A40: Stressed CET1 capital | B40: =B38+B39 -> 3032.6393 | C40: =C38+C39 -> 2962.1721
A41: Pro forma RWA (base case) | B41: ='Deal B Pro Forma'!$B$60 -> 29450 | C41: ='Deal C Pro Forma'!$B$60 -> 27050
A42: Plus: EAD migration overlay | B42: =B33 -> 458.49375 | C42: =C33 -> 50.0175
A43: Stressed RWA | B43: =B41+B42 -> 29908.494 | C43: =C41+C42 -> 27100.018
A44: Base-case pro forma CET1 ratio, after the raise | B44: ='Deal B Pro Forma'!$B$77 -> 0.11 | C44: ='Deal C Pro Forma'!$B$77 -> 0.11
A45: STRESSED CET1 RATIO — with the equity raise | B45: =B40/B43 -> 0.10139726 | C45: =C40/C43 -> 0.10930517
A46: Stressed CET1 capital WITHOUT the equity raise | B46: ='Deal B Pro Forma'!$B$57-B26 -> 1978.1393 | C46: ='Deal C Pro Forma'!$B$57-C26 -> 2774.6721
A47: STRESSED CET1 RATIO — without the equity raise | B47: =B46/B43 -> 0.066139716 | C47: =C46/C43 -> 0.10238636
A48: Breaches the 7.0% regulatory minimum without a raise? | B48: =IF(B47<'Cover & Assumptions'!$B$22,"YES — BREACH","No") -> YES — BREACH | C48: =IF(C47<'Cover & Assumptions'!$B$22,"YES — BREACH","No") -> No
A49: Stressed headroom over the 11.0% internal target (bps) | B49: =(B45-'Cover & Assumptions'!$B$21)*10000 -> -86.027409 | C49: =(C45-'Cover & Assumptions'!$B$21)*10000 -> -6.9482607
A50: Additional equity needed to hold the 11.0% target through the stress | B50: =MAX(0,'Cover & Assumptions'!$B$21*B43-B40) -> 257.29502 | C50: =MAX(0,'Cover & Assumptions'!$B$21*C43-C40) -> 18.829799 | E50: On top of the raise already sized at close
A52: E. STRESSED EARNINGS AND EPS (FY2026E)
A53: Item | B53: Deal B | C53: Deal C | E53: Note
A54: Base-case pro forma pre-tax income | B54: ='Deal B Pro Forma'!$B$103 -> 990.5775 | C54: ='Deal C Pro Forma'!$B$103 -> 635.48375
A55: Less: stress provision expense | B55: =-B25 -> -279.5415 | C55: =-C25 -> -18.01064
A56: Stressed pre-tax income | B56: =B54+B55 -> 711.036 | C56: =C54+C55 -> 617.47311
A57: Stressed net income | B57: =B56*(1-'Cover & Assumptions'!$B$20) -> 526.16664 | C57: =C56*(1-'Cover & Assumptions'!$B$20) -> 456.9301
A58: Pro forma shares outstanding (mm) | B58: ='Deal B Pro Forma'!$B$72 -> 143.96591 | C58: ='Deal C Pro Forma'!$B$72 -> 124.26136
A59: STRESSED PRO FORMA EPS ($) | B59: =B57/B58 -> 3.6548002 | C59: =C57/C58 -> 3.6771695
A60: Base-case pro forma EPS ($) | B60: ='Deal B Pro Forma'!$B$110 -> 5.0916731 | C60: ='Deal C Pro Forma'!$B$110 -> 3.7844263
A61: EPS decline versus base case | B61: =B59/B60-1 -> -0.28220053 | C61: =C59/C60-1 -> -0.028341622
A62: Bank A standalone stressed pre-tax income | B62: ='Standalone Summary'!$C$122-'Standalone Summary'!$C$124*'Cover & Assumptions'!$B$96 -> 584.123 | C62: ='Standalone Summary'!$C$122-'Standalone Summary'!$C$124*'Cover & Assumptions'!$B$96 -> 584.123 | E62: Meridian alone also carries the +50bps stress on its own book
A63: Bank A standalone stressed EPS ($) | B63: =B62*(1-'Cover & Assumptions'!$B$20)/'Cover & Assumptions'!$B$24 -> 3.6020918 | C63: =B62*(1-'Cover & Assumptions'!$B$20)/'Cover & Assumptions'!$B$24 -> 3.6020918
A64: STRESSED EPS ACCRETION / (DILUTION) versus standalone | B64: =B59/B63-1 -> 0.014632723 | C64: =C59/C63-1 -> 0.020842808
A66: F. RISK-ADJUSTED RETURN — THE STRESS APPLIED PERMANENTLY TO YEAR 3
A67: Item | B67: Deal B | C67: Deal C | E67: Note
A68: Acquired book gross receivables — FY2028E | B68: ='Standalone Summary'!$E$137 -> 10049.05 | C68: ='Standalone Summary'!$E$150 -> 399.32672
A69: Year-3 stress provision on the acquired book | B69: =B68*('Cover & Assumptions'!$B$94+'Cover & Assumptions'!$B$95*B20) -> 330.61374 | C69: =C68*('Cover & Assumptions'!$B$94+'Cover & Assumptions'!$B$95*C20) -> 12.658657
A70: Base-case Year-3 deal-attributable after-tax earnings | B70: ='Deal B Pro Forma'!$D$127 -> 651.85777 | C70: ='Deal C Pro Forma'!$D$127 -> 188.24511
A71: Stressed Year-3 deal-attributable after-tax earnings | B71: =B70-B69*(1-'Cover & Assumptions'!$B$20) -> 407.2036 | C71: =C70-C69*(1-'Cover & Assumptions'!$B$20) -> 178.8777
A72: Total capital committed | B72: ='Deal B Pro Forma'!$B$129 -> 2837.7 | C72: ='Deal C Pro Forma'!$B$129 -> 1307.8
A73: Base-case Year-3 ROIC on capital committed | B73: ='Deal B Pro Forma'!$D$131 -> 0.22971342 | C73: ='Deal C Pro Forma'!$D$131 -> 0.14394029
A74: STRESS-ADJUSTED YEAR-3 ROIC | B74: =B71/B72 -> 0.14349776 | C74: =C71/C72 -> 0.13677757
A75: Base-case ROIC advantage of Deal B over Deal C (bps) | B75: =(B73-C73)*10000 -> 857.73133
A76: Stress-adjusted ROIC advantage of Deal B over Deal C (bps) | B76: =(B74-C74)*10000 -> 67.201963
A77: Read together: Deal B's return advantage is largely a credit-risk premium. One moderate recession — applied to a book already running a 4.6% charge-off rate and deteriorating — collapses it, while simultaneously consuming the capital cushion the raise was meant to rebuild. Deal C's return is lower but survives the same shock close to intact.
A79: G. STRESS SUMMARY
A80: Headline | B80: Deal B | C80: Deal C
A81: Stressed CET1 ratio, with the equity raise | B81: =B45 -> 0.10139726 | C81: =C45 -> 0.10930517
A82: Stressed CET1 ratio, without the equity raise | B82: =B47 -> 0.066139716 | C82: =C47 -> 0.10238636
A83: Stressed Year-1 EPS ($) | B83: =B59 -> 3.6548002 | C83: =C59 -> 3.6771695
A84: Stressed Year-1 EPS accretion versus standalone | B84: =B64 -> 0.014632723 | C84: =C64 -> 0.020842808
A85: Stress-adjusted Year-3 ROIC | B85: =B74 -> 0.14349776 | C85: =C74 -> 0.13677757
A86: Additional equity needed to hold the target through the stress ($mm) | B86: =B50 -> 257.29502 | C86: =C50 -> 18.829799
